dataset_support-0.1.3.dist-info/METADATA
dataset_support-0.1.3.dist-info/WHEEL
dataset_support/__init__.py
dataset_support/dataset_support.cpython-311-darwin.so
dataset_support-0.1.3.dist-info/RECORD
