Metadata-Version: 2.3
Name: dataset_support
Version: 0.1.3
Classifier: Programming Language :: Rust
Classifier: Programming Language :: Python :: Implementation :: CPython
Classifier: Programming Language :: Python :: Implementation :: PyPy
Requires-Dist: numpy >=1.16.0
Requires-Python: >=3.8
